{
  "db_name": "PostgreSQL",
  "query": "SELECT projects.user_id AS user_id, projects.id AS project_id FROM tasks JOIN projects ON tasks.project_id = projects.id WHERE tasks.id = $1",
  "describe": {
    "columns": [
      {
        "ordinal": 0,
        "name": "user_id",
        "type_info": "Varchar"
      },
      {
        "ordinal": 1,
        "name": "project_id",
        "type_info": "Int4"
      }
    ],
    "parameters": {
      "Left": [
        "Int4"
      ]
    },
    "nullable": [
      false,
      false
    ]
  },
  "hash": "5269d0beb217c4e8cbb816bea986710eae15c483cb2cd1938f76a34f933e6802"
}
