{
  "db_name": "PostgreSQL",
  "query": "SELECT id, user_ids as members FROM discussions WHERE task_id = $1 AND proposal_id = $2 AND $3 = ANY(user_ids)",
  "describe": {
    "columns": [
      {
        "ordinal": 0,
        "name": "id",
        "type_info": "Int4"
      },
      {
        "ordinal": 1,
        "name": "members",
        "type_info": "TextArray"
      }
    ],
    "parameters": {
      "Left": [
        "Int4",
        "Int4",
        "Text"
      ]
    },
    "nullable": [
      false,
      false
    ]
  },
  "hash": "088efac9a44efdbfb67b4ba81f129b9e4800d36a9dfd4f730dbb88e616627c8f"
}
